[
	{
		"id": "1",
		"name": "Fragile Handle with Care Coquette Bunny Round Waterproof Vinyl Sticker",
		"price": 25.00,
		"stocks": 10,
		"gallery": ["main.png", "sample.png", "gallery-1.png", "gallery-2.png", "gallery-3.png", "gallery-4.png", "gallery-5.png", "gallery-6.png"]
	},
	{
		"id": "2",
		"name": "Karameru Fan-made Penguin on Iceberg Waterproof Vinyl Sticker",
		"price": 35.00,
		"stocks": 5,
		"gallery": ["main.png", "sample.png"]
	},
	{
		"id": "3",
		"name": "Karameru Fan-made Panda/Axolotl/Penguin Waterproof Vinyl Sticker",
		"price": 15.00,
		"stocks": 8,
		"gallery": ["main.png", "sample.png", "gallery-1.png", "gallery-2.png", "gallery-3.png", "gallery-4.png", "gallery-5.png", "gallery-6.png"]
	},
	{
		"id": "4",
		"name": "Persona 5 Fan-made Cute Morgana Waterproof Vinyl Sticker",
		"price": 15.00,
		"stocks": 8,
		"gallery": ["main.png", "sample.png"]
	},
	{
		"id": "5",
		"name": "Toilet Bound Hanako-San Fan-made Mokke Candy Waterproof Vinyl Sticker",
		"price": 15.00,
		"stocks": 8,
		"gallery": ["gallery-1.png", "gallery-2.png", "gallery-3.png", "gallery-4.png", "gallery-5.png", "gallery-6.png", "gallery-7.png", "gallery-8.png"]
	},
	{
		"id": "6",
		"name": "Toilet Bound Hanako-San Fan-made Four Mokke Waterproof Vinyl Sticker",
		"price": 15.00,
		"stocks": 8,
		"gallery": ["main.png", "sample.png"]
	},
	{
		"id": "7",
		"name": "Swavemente Funny Cute Waterproof Vinyl Sticker",
		"price": 15.00,
		"stocks": 8,
		"gallery": ["main.png", "sample.png"]
	},
	{
		"id": "8",
		"name": "Anime Cry Funny Cute Waterproof Vinyl Sticker",
		"price": 15.00,
		"stocks": 8,
		"gallery": ["main.png", "sample.png"]
	}
